oa3_responses_validator/__init__.py
oa3_responses_validator/main.py
oa3_responses_validator/validator.py
oa3_responses_validator-1.0.0.dist-info/LICENSE
oa3_responses_validator-1.0.0.dist-info/METADATA
oa3_responses_validator-1.0.0.dist-info/WHEEL
oa3_responses_validator-1.0.0.dist-info/entry_points.txt
oa3_responses_validator-1.0.0.dist-info/RECORD
